bootloader.py
bootloader_mode.py
configuration.py
europi.py
europi_config.py
europi_display.py
europi_hardware.py
europi_log.py
europi_script.py
file_utils.py
setup.py
ui.py
version.py
experimental/__init__.py
experimental/a_to_d.py
experimental/bisect.py
experimental/bitarray.py
experimental/custom_font.py
experimental/euclid.py
experimental/experimental_config.py
experimental/http_server.py
experimental/knobs.py
experimental/math_extras.py
experimental/osc.py
experimental/quantizer.py
experimental/random_extras.py
experimental/rtc.py
experimental/screensaver.py
experimental/settings_menu.py
experimental/thread.py
experimental/wifi.py
experimental/clocks/__init__.py
experimental/clocks/clock_source.py
experimental/clocks/ds1307.py
experimental/clocks/ds3231.py
experimental/clocks/ntp.py
experimental/clocks/null_clock.py
experimental/fonts/freesans14.py
experimental/fonts/freesans17.py
experimental/fonts/freesans20.py
experimental/fonts/freesans24.py
experimental/fonts/ubuntumono14.py
experimental/fonts/ubuntumono17.py
experimental/fonts/ubuntumono20.py
experimental/fonts/ubuntumono24.py
micropython_europi.egg-info/PKG-INFO
micropython_europi.egg-info/SOURCES.txt
micropython_europi.egg-info/dependency_links.txt
micropython_europi.egg-info/top_level.txt
tools/__init__.py
tools/about.py
tools/calibrate.py
tools/conf_edit.py
tools/diagnostic.py
tools/experimental_conf_edit.py