Metadata-Version: 2.1
Name: micropython-europi
Version: 0.20.0
Summary: EuroPi module for MicroPython
Home-page: https://github.com/Allen-Synthesis/EuroPi
Author: Allen Synthesis
Author-email: contact@allensynthesis.co.uk
License: Apache 2.0
